skoobpy/__init__.py
skoobpy/__main__.py
skoobpy/skoobpy.py
skoobpy-0.1.3.dist-info/LICENSE
skoobpy-0.1.3.dist-info/METADATA
skoobpy-0.1.3.dist-info/WHEEL
skoobpy-0.1.3.dist-info/top_level.txt
skoobpy-0.1.3.dist-info/RECORD
