Metadata-Version: 2.1
Name: skoobpy
Version: 0.1.3
Summary: extracts user's desired books from Skoob.com.br
Home-page: https://github.com/Diegoslourenco/skoobpy
Author: Diego Lourenço
Author-email: diego.lourenco15@gmail.com
License: MIT
Platform: Any
Classifier: Development Status :: 3 - Alpha
Classifier: License :: OSI Approved :: MIT License
Classifier: Operating System :: OS Independent
Classifier: Programming Language :: Python
